Metadata-Version: 2.1
Name: onn
Version: 0.0.2
Summary: Online Neural Network
Home-page: https://github.com/alison-carrera/onn
Author: Alison Carrera
Author-email: alison.carrera2007@gmail.com
License: Apache 2.0
Platform: UNKNOWN
